{
  "name": "Another Mount Rokkon",
  "slug": "cr2",
  "prepull": [["     T     ", "H         M", "     R     "], ["TM N | HR S"]],
  "planners": [
    {
      "phase": "p1",
      "label": "ghosts",
      "url": "https://imgur.com/FrxdWyq"
    },
    {
      "phase": "p1",
      "label": "2nd-adds",
      "url": "https://www.youtube.com/watch?v=3HItOmXk0AA"
    },
    {
      "phase": "p2",
      "label": "exaflares",
      "url": "https://raidplan.io/plan/sXAziueXklqC-twa"
    },
    {
      "phase": "p2",
      "label": "limit-cut",
      "url": "https://raidplan.io/plan/SaCYk_n_5ZiJFOMK"
    },
    {
      "phase": "p2",
      "label": "rousing-reincarnation-2",
      "url": "https://ff14.toolboxgaming.space/?id=938195953989861&preview=1#1"
    },
    {
      "phase": "p2",
      "label": "alt-rousing-reincarnation-2",
      "url": "https://imgur.com/a/GjjNBzC"
    },
    {
      "phase": "p3",
      "label": "scarlet",
      "url": "https://imgur.com/hvGBUDU"
    },
    {
      "phase": "p3",
      "label": "azure",
      "url": "https://www.twitch.tv/lysorm/clip/ShinySourGaurTwitchRaid-KrOLY102K0k71pGu"
    },
    {
      "phase": "p3",
      "label": "shadow-twin",
      "url": "https://raidplan.io/plan/yWjyvLysjEe6FpJU"
    },
    {
      "phase": "p3",
      "label": "shadow-twin-2",
      "url": "https://imgur.com/a/K980Plo"
    }
  ],
  "unlock": "https://ffxiv.consolegameswiki.com/wiki/Variant_and_Criterion_Dungeons#Unlock_2",
  "videos": [
    {
      "label": "Boss 1 - Big Kobe Guide",
      "url": "https://www.youtube.com/watch?v=AtWaOqBRlzk&pp=ygUhYW5vdGhlciBzaWwnZGlobiBzdWJ0ZXJyYW5lIGd1aWRl"
    },
    {
      "label": "Boss 2 - Big Kobe Guide",
      "url": "https://www.youtube.com/watch?v=-fMnILFQMi0&pp=ygUhYW5vdGhlciBzaWwnZGlobiBzdWJ0ZXJyYW5lIGd1aWRl"
    },
    {
      "label": "Boss 3 - Big Kobe Guide",
      "url": "https://www.youtube.com/watch?v=QhmdV-AIYl0&pp=ygUhYW5vdGhlciBzaWwnZGlobiBzdWJ0ZXJyYW5lIGd1aWRl"
    },
    {
      "label": "Mrhappy Walkthrough and Commentary",
      "url": "https://www.youtube.com/watch?v=Fhv2saxo2_8&pp=ygUaYW5vdGhlciBtb3VudCByb2trb24gZ3VpZGU%3D"
    }
  ]
}
